sonarcloudx1/__init__.py
sonarcloudx1/abstract.py
sonarcloudx1/componentstree.py
sonarcloudx1/duplications.py
sonarcloudx1/factories.py
sonarcloudx1/issues.py
sonarcloudx1/measures.py
sonarcloudx1/metrics.py
sonarcloudx1/project.py
sonarcloudx1/projectanalyses.py
sonarcloudx1/projectbranches.py
sonarcloudx1/projectlinks.py
sonarcloudx1/projectpullrequests.py
sonarcloudx1/rules.py
sonarcloudx1/supportedProgramingLanguages.py
sonarcloudx1/users.py
sonarcloudx1-0.12.0.dist-info/METADATA
sonarcloudx1-0.12.0.dist-info/WHEEL
sonarcloudx1-0.12.0.dist-info/top_level.txt
sonarcloudx1-0.12.0.dist-info/RECORD
