Metadata-Version: 2.1
Name: sonarcloudx1
Version: 0.12.0
Summary: lib para buscar wrapper SonarCloud
Home-page: https://gitlab.com/immigrant-data-driven-development/libs/application/sonarcloud.git
Author: Carlos Henrique Maulaz de Freitas
Author-email: carlosmaulaz@gmail.com
License: UNKNOWN
Platform: UNKNOWN
Classifier: Programming Language :: Python :: 3
Classifier: License :: OSI Approved :: MIT License
Classifier: Operating System :: OS Independent
Requires-Dist: factory-boy
Requires-Dist: python-sonarqube-api
